4_controller_design.v
//controller module; written by GYMS team
//control unit of processor
module controller(
	input [3:0]opcode,//opcode
	output reg mem_signal_write,//memory write signal
	output reg reg_signal_write//register write signal
);
	//classification of instructions
	parameter mem_data_inst = 3'b000,//ldm,stm
		  reg_data_inst = 3'b001,//ldr,mov
		  andor_inst = 3'b010,//and,or
		  notxor_inst = 3'b011,//not,xor
		  shift_inst = 3'b100,//shl,shr
		  addsub_inst = 3'b101,//add,sub
		  div_inst = 3'b110;//div
	always@(*)//combinational logic for control signal generation
		begin
			case(opcode[3:1])
				mem_data_inst: begin
					//for ldm, write to reg file; for stm, read from reg file
					//for ldm, read from data mem; for stm, write to data mem
					reg_signal_write <= ~opcode[0];
					mem_signal_write <= opcode[0];
				end
				reg_data_inst,andor_inst,notxor_inst: begin
					//for: ldr,mov,and,or,not,xor only write to reg file
					reg_signal_write <= 1'b1;
					mem_signal_write <= 1'b0;
				end
				addsub_inst,div_inst,shift_inst: begin
					//for: add,sub,div,shl,shr only write to reg file
					reg_signal_write <= 1;
					mem_signal_write <= 0;
				end
			endcase
		end
endmodule

4_datapath_design.v
//datapath module; written by GYMS team
//datapath of processor
module datapath #(parameter nop_width = 3)(
	input clock,//processor clock
	input reset,//processor reset
	input mem_signal_write,//mem write signal
	input reg_signal_write,//reg write signal
	output [3:0]opcode,//opcode
	output zero_flag,//zero flag; triggers if resultant=0
	output error_flag//error flag; triggers if resulant=x or division by zero
);
	//classification of instructions
	parameter mem_data_inst = 3'b000,//ldm,stm
		  reg_data_inst = 3'b001,//ldr,mov
		  andor_inst = 3'b010,//and,or
		  notxor_inst = 3'b011,//not,xor
		  shift_inst = 3'b100,//shl,shr
		  addsub_inst = 3'b101,//add,sub
		  div_inst = 3'b110,//div
		  nop = 3'b111;//no operation
	//classification of operations
	parameter bit_and = 4'b0000,//and
		  bit_or = 4'b0001,//or
		  bit_xor = 4'b0010,//xor
		  bit_not = 4'b0011,//not
		  shift_log_left = 4'b0100,//logic shift left
		  shift_ari_left = 4'b0101,//arith shift left
		  shift_log_right = 4'b0110,//logic shift right
		  shift_ari_right = 4'b0111,//arith shift right
		  arith_add = 4'b1000,//add
		  arith_sub = 4'b1001,//sub
		  arith_div = 4'b1010;//div
	//data memory read-write ports
	reg [7:0]mem_addr_rw;//shared address
	reg [15:0]mem_data_write;//write data
	wire [15:0]mem_data_read;//read data
	//register file read-write ports
	reg [3:0]reg_addr_write;//write address
	reg [3:0]reg_addr_read1;//1st read address
	reg [3:0]reg_addr_read2;//2nd read address
	reg [15:0]reg_data_write;//write data
	wire [15:0]reg_data_read1;//1st read data
	wire [15:0]reg_data_read2;//2nd read data
	//instruction memory ports
	reg [7:0]program_counter;//program counter
	wire [15:0]instruction;//instruction extracted
	//arithmetic and logical unit (alu) ports
	reg [3:0]operation;//alu operation
	reg [15:0]alu_op1;//alu 1st operand
	reg [15:0]alu_op2;//alu 2nd operand
	wire [15:0]alu_res;//alu result
	/*stages of pipelining implememted are:
	IF = instruction fetch
	ID = instruction decode
	EX = execute operation
	MEM = memory access
	WB = write back registers*/
	//pipelining registers between IF and ID stages
	reg [3:0]IF_ID_opcode;
	reg [7:0]IF_ID_program_counter;
	reg [15:0]IF_ID_instruction;
	//pipelining registers between ID and EX stages
	reg [3:0]ID_EX_reg_addr_write;
	reg [3:0]ID_EX_operation;
	reg [3:0]ID_EX_opcode;
	reg [15:0]ID_EX_instruction;
	reg [15:0]ID_EX_reg_data_read1;
	reg [15:0]ID_EX_reg_data_read2;
	reg [15:0]ID_EX_reg_data_write;
	reg [15:0]ID_EX_mem_data_write;
	//pipelining registers between EX and MEM stages
	reg EX_MEM_mem_signal_write;
	reg [3:0]EX_MEM_reg_addr_write;
	reg [3:0]EX_MEM_opcode;
	reg [15:0]EX_MEM_alu_res;
	reg [15:0]EX_MEM_reg_data_write;
	reg [15:0]EX_MEM_mem_data_write;
	//pipelining registers between MEM and WB stages
	reg MEM_WB_reg_signal_write;
	reg [3:0]MEM_WB_reg_addr_write;
	reg [15:0]MEM_WB_reg_data_write;
	//nop operation related variables
	wire [nop_width-1:0]count_ID;//ID stage NOP counter
	wire [nop_width-1:0]count_EX;//EX stage NOP counter
	reg counter_ID_en;//enable signal for ID counter
	reg counter_EX_en;//enable signal for EX counter
	//instruction fetch stage
	always@(posedge clock)//sequential logic for extracting instructions
		begin
			if(reset)//synchronous reset; and if high
				program_counter <= 8'd0;//initialise program counter
			else
				program_counter <= program_counter + 8'd1;//continue incrementing
		end
	//instantiating instruction memory
	instr_memory IM(
			.program_counter(program_counter),
			.instruction(instruction)
	);
	//intermediate between IF and ID stages
	always @(posedge clock)//sequential logic for moving these into registers
		begin
			IF_ID_instruction <= instruction;
			IF_ID_program_counter <= program_counter;
			IF_ID_opcode <= instruction[15:12];
		end
	//instruction decode stage
	always@(*)//combinational logic to decode data from instruction
		begin
			//consider the instruction classification
			case(IF_ID_opcode[3:1])
				//includes ldm and stm
				mem_data_inst: begin
					mem_addr_rw = IF_ID_instruction[7:0];//address allocation
					if(IF_ID_opcode[0] == 1'b0)//if ldm
						begin
							reg_addr_write = IF_ID_instruction[11:8];//write to reg
							reg_data_write = mem_data_read;//write this from mem
						end
					else//if stm
						begin
							reg_addr_read1 = IF_ID_instruction[11:8];//read from reg
							mem_data_write = reg_data_read1;//write this to mem
						end
					end
				//includes ldr and mov
				reg_data_inst: begin
					reg_addr_write = IF_ID_instruction[11:8];//write to this register
					if(IF_ID_opcode[0] == 1'b0)//if ldr
						begin
							//assigning immediate from instruction
							reg_data_write = {8'b0,IF_ID_instruction[7:0]};
						end
					else//mov
						begin
							reg_addr_read1 = IF_ID_instruction[7:4];//read from reg
							reg_data_write = reg_data_read1;//write this from reg
						end
					end
				//includes and,or,add,sub
				andor_inst,addsub_inst: begin
					reg_addr_read1 = IF_ID_instruction[7:4];//read from this register
					reg_addr_read2 = IF_ID_instruction[3:0];//read from this register too
					reg_addr_write = IF_ID_instruction[11:8];//write to this register
					if(IF_ID_opcode[3:1]==andor_inst)
						//operation is and or or
						operation = (IF_ID_opcode[0] == 1'b0)? bit_and : bit_or;
					else if(IF_ID_opcode[3:1]==addsub_inst)
						//operation is add or sub
						operation = (IF_ID_opcode[0] == 1'b0)? arith_add : arith_sub;
					end
				//includes not,xor,div
				notxor_inst,div_inst: begin
					reg_addr_write = IF_ID_instruction[11:8];//write to this register
					reg_addr_read1 = IF_ID_instruction[7:4];//read from this register
					if(IF_ID_opcode[0] == 0)//if xor or div
						begin
							//read from this register too
							reg_addr_read2 = IF_ID_instruction[3:0];									
							if(IF_ID_opcode[3:1]==notxor_inst)
								operation = bit_xor;//operation is xor
							else if(IF_ID_opcode[3:1]==div_inst)
								operation = arith_div;//operation is div
						end
					//if not instruction
					else if((IF_ID_opcode[3:1]==notxor_inst)&&(IF_ID_opcode[0] == 1'b1))
						begin
							operation = bit_not;//operation is not
						end
					end
				//includes shl and shr
				shift_inst: begin
					reg_addr_write = IF_ID_instruction[11:8];//write to this register
					reg_addr_read1 = IF_ID_instruction[7:4];//read from this register
					if(IF_ID_instruction[3:2]==2'b00)//logical shift
						begin
							if(IF_ID_opcode[0] == 1'b0)
								operation = shift_log_left;//logic shift left
							else
								operation = shift_log_right;//logic shift right
						end
					else if(IF_ID_instruction[3:2]==2'b11)//arithmetic shift
						begin
							if(IF_ID_opcode[0] == 1'b0)
								operation = shift_ari_left;//arith shift left
							else
								operation = shift_ari_right;//arith shift right
						end
					end
				//includes only nop
				nop: begin
					counter_ID_en = 1'b1;//enable the counter
					//rest all need not be cared; so this is written
					reg_addr_read1 = 4'dx;
					reg_addr_read2 = 4'dx;
					reg_addr_write = 4'dx;
					operation = 4'dx;
					reg_data_write = 16'dx;
					mem_addr_rw = 8'dx;
					mem_data_write = 16'dx;
					end
			endcase
		end
	//instantiate the counter for NOP
	counter #(nop_width) COUNT_ID(.clock(clock),.reset(reset),.en(counter_ID_en),.count(count_ID));
	//intermediate between ID and EX stages
	always@(posedge clock)//sequential logic for moving these into registers
		begin
			ID_EX_reg_addr_write <= reg_addr_write;
			ID_EX_mem_data_write <= mem_data_write;
			ID_EX_reg_data_read1 <= reg_data_read1;
			ID_EX_reg_data_read2 <= reg_data_read2;
			ID_EX_operation <= operation;
			ID_EX_opcode <= IF_ID_opcode;
			ID_EX_instruction <= IF_ID_instruction;
			ID_EX_reg_data_write <= reg_data_write;
		end
	//execute stage
	always@(*)//combinational logic to decode operands for the ALU
		begin
			//consider the instruction classification
			case(ID_EX_opcode[3:1])
				//includes and,or,add,sub
				andor_inst, addsub_inst: begin
					//two register sources
					alu_op1 = ID_EX_reg_data_read1;//move this read1 data to alu
					alu_op2 = ID_EX_reg_data_read2;//move this read2 data to alu
					end
				//includes not,xor,div
				notxor_inst, div_inst: begin
					//one sure-shot register source
					alu_op1 = ID_EX_reg_data_read1;//move this read1 data to alu
					if(ID_EX_opcode[0] == 1'b0)
						//the second register source instructions
						alu_op2 = ID_EX_reg_data_read2;//move this read2 data to alu
					else if((ID_EX_opcode[3:1] == notxor_inst) && (IF_ID_opcode[0] == 1'b1))
						begin
							//1's or 2's complement condition based operand
							if(ID_EX_instruction[3:0] == 4'b1111)
								alu_op2 = 16'd1;
							else if(ID_EX_instruction[3:0] == 4'b0000)
								alu_op2 = 16'd0;
						end
					end
				//includes shl,shr
				shift_inst: begin
					//one register source and condition based operand
					alu_op1 = ID_EX_reg_data_read1;//move this data to alu
					alu_op2 = {14'd0,ID_EX_instruction[1:0]};//move this data to alu too
					end
				//includes only nop
				nop: begin
					counter_EX_en = 1'b1;//enable the counter
					//rest all need not be cared; so this is written
					alu_op1 = 16'dx;
					alu_op2 = 16'dx;
					end
			endcase
		end
	//instantiating the counter for NOP
	counter #(nop_width) COUNT_EX(.clock(clock),.reset(reset),.en(counter_EX_en),.count(count_EX));
	//instantiating arithmetic and logical unit (alu)
	arithmetic_logical_unit ALU(
			.operation(ID_EX_operation),
			.alu_op1(alu_op1),
			.alu_op2(alu_op2),
			.alu_res(alu_res),
			.zero_flag(zero_flag),
			.error_flag(error_flag)
	);
	//intermediate between EX and MEM stages
	always@(posedge clock)//sequential logic for moving these into registers
		begin
			EX_MEM_mem_signal_write <= mem_signal_write;
			EX_MEM_mem_data_write <= ID_EX_mem_data_write;
			EX_MEM_opcode <= ID_EX_opcode;
			EX_MEM_reg_addr_write <= ID_EX_reg_addr_write;
			//reg_data_write has two different results: alu_res or reg_data_write
			if((ID_EX_opcode[3:1]==mem_data_inst) && (ID_EX_opcode[0] == 1'b0))
				EX_MEM_reg_data_write <= ID_EX_reg_data_write;//push the reg_write_data
			else if(ID_EX_opcode[3:1]==reg_data_inst)
				EX_MEM_reg_data_write <= ID_EX_reg_data_write;//push the reg_write_data
			else
				EX_MEM_reg_data_write <= alu_res;//push the alu result
		end
	assign opcode = EX_MEM_opcode;//final opcode for showing instruction type to be seen at waveform
	//memory access stage
	//instantiating data memory
	data_memory DM(
			.clock(clock),
			.mem_signal_write(EX_MEM_mem_signal_write),
			.mem_addr_rw(mem_addr_rw),
			.mem_data_read(mem_data_read),
			.mem_data_write(EX_MEM_mem_data_write)
	);
	//intermediate between MEM and WB stages
	always@(posedge clock)//sequential logic for moving these into registers
		begin
			MEM_WB_reg_addr_write <= EX_MEM_reg_addr_write;
			MEM_WB_reg_signal_write <= reg_signal_write;
			MEM_WB_reg_data_write <= EX_MEM_reg_data_write;
		end
	//write back registers stage
	//instantiating register file
	register_file RF(
			.clock(clock),
			.reg_signal_write(MEM_WB_reg_signal_write),
			.reg_addr_write(MEM_WB_reg_addr_write),
			.reg_data_write(MEM_WB_reg_data_write),
			.reg_addr_read1(reg_addr_read1),
			.reg_addr_read2(reg_addr_read2),
			.reg_data_read1(reg_data_read1),
			.reg_data_read2(reg_data_read2)
	);
endmodule
//code for the NOP counter
module counter #(parameter width = 8)(//default parameter is 8
	input clock,//processor clock
	input reset,//processor reset
	input en,//counter enable
	output reg [width-1:0]count//count value
);
	always@(posedge clock)//sequential logic to count
		begin
			//counts only if enabled
			if(reset && en)
				count <= 'd0;
			else if (en)
				count <= count + 'd1;
		end
endmodule
//arithmetic and logical unit module; written by GYMS team
//alu of processor
module arithmetic_logical_unit(
	input [3:0]operation,//alu operation
	input [15:0]alu_op1,//alu 1st operand
	input [15:0]alu_op2,//alu 2nd operand
	output reg [15:0]alu_res,//alu result
	output reg zero_flag,//zero flag
	output reg error_flag//error flag
);
	//classification of operations
	parameter bit_and = 4'b0000,//and
		  bit_or = 4'b0001,//or
		  bit_xor = 4'b0010,//xor
		  bit_not = 4'b0011,//not
		  shift_log_left = 4'b0100,//logic shift left
		  shift_ari_left = 4'b0101,//arith shift left
		  shift_log_right = 4'b0110,//logic shift right
		  shift_ari_right = 4'b0111,//arith shift right
		  arith_add = 4'b1000,//add
		  arith_sub = 4'b1001,//sub
		  arith_div = 4'b1010;//div
	always @(*)//combinational logic for the operation selection
		begin
			case(operation)//perform based on the given operation
				bit_and: alu_res = alu_op1 & alu_op2;//and
				bit_or: alu_res = alu_op1 - alu_op2;//or
				bit_xor: alu_res = alu_op1 / alu_op2;//xor
				bit_not: alu_res = (~alu_op1) + alu_op2;//1's or 2's complement
				shift_log_left: alu_res = alu_op1 << alu_op2;//logical left shift
				shift_ari_left: alu_res = alu_op1 <<< alu_op2;//arithmetic left shift
				shift_log_right: alu_res = alu_op1 >> alu_op2;//logical right shift
				shift_ari_right: alu_res = alu_op1 >>> alu_op2;//arithmetic right shift
				arith_add: alu_res = alu_op1 + alu_op2;//add
				arith_sub: alu_res = alu_op1 - alu_op2;//sub
				arith_div: alu_res = (alu_op2==16'd0)?(16'dx):(alu_op1 / alu_op2);//div
			endcase
			zero_flag = (alu_res==16'd0)?1'b1:1'b0;//if result is zero
			error_flag =(alu_res==16'dx)?1'b1:1'b0;//if result can't be made
		end
endmodule
//memories and register file modules; written by GYMS team
//instruction memory of processor
module instr_memory(
	input [7:0]program_counter,//program counter
	output [15:0]instruction//instruction
);
	reg [15:0]instruction_memory[0:255];//instruction memory of 256 words each of 16 bits
	assign instruction = instruction_memory[program_counter];//instruction assignment
endmodule
//data memory of processor
module data_memory(
	input clock,//processor clock
	input mem_signal_write,//write signal
	input [7:0]mem_addr_rw,//shared address
	input [15:0]mem_data_write,//write data
	output [15:0]mem_data_read//read data
);
	reg [15:0]data_memory[0:255];//data memory of 256 words each of 16 bits
	integer i;
	initial//initial values are made zeroes
		begin
			for(i=0;i<256;i=i+1)
				data_memory[i] <= 16'd0;//initialising memory words as zeroes
		end
	always@(posedge clock)//sequential logic for writing to memory
		begin
			if(mem_signal_write==1'b1)//writing
				data_memory[mem_addr_rw] <= mem_data_write;//write assignment
		end
	assign mem_data_read = (mem_signal_write==1'b0)?data_memory[mem_addr_rw]:16'dx;//read assignment
endmodule
//register file of processor
module register_file(
	input clock,//clock of processor
	input reg_signal_write,//write signal
	input [3:0]reg_addr_write,//write address
	input [3:0]reg_addr_read1,//read address 1
	input [3:0]reg_addr_read2,//read address 2
	input [15:0]reg_data_write,//write data
	output [15:0]reg_data_read1,//read data 1
	output [15:0]reg_data_read2//read data 2
);
	reg [15:0]register_file[0:15];//register file
	integer i;
	initial//initial values are made zeroes
		begin
			for(i=0;i<16;i=i+1)
				register_file[i] <= 16'd0;//initialising register words as zeroes
		end
	always@(posedge clock)//sequential logic for writing to register file
		begin
			if(reg_signal_write==1'b1)//writing
				register_file[reg_addr_write] <= reg_data_write;//write assignment
		end
	assign reg_data_read1 = register_file[reg_addr_read1];//read assignment 1
	assign reg_data_read2 = register_file[reg_addr_read2];//read assignment 2
endmodule

5_processor_design.v
//processor module; written by GYMS team
`include "4_controller_design.v"
`include "4_datapath_design.v"
//combined datapath and controller of processor
module processor(
	input clock,//processor clock
	input reset,//processor reset
	output zero_flag,//zero flag; triggers if resultant==0
	output error_flag//error flag; triggers if resulant=x or division by zero
);
	wire mem_signal_write;//data memory write signal
	wire reg_signal_write;//register file write signal
	wire [3:0]opcode;//opcode
	//instantiating the datapath
	datapath DATA(
			.clock(clock),
			.reset(reset),
			.mem_signal_write(mem_signal_write),
			.reg_signal_write(reg_signal_write),
			.opcode(opcode),
			.zero_flag(zero_flag),
			.error_flag(error_flag)
	);
	//instantiating the controller
	controller CONTROL(
			.opcode(opcode),
			.mem_signal_write(mem_signal_write),
			.reg_signal_write(reg_signal_write)
	);
endmodule

5_processor_testbench.v
//GYMS-16 testbench; written by GYMS team
`timescale 1ns / 1ps//time unit 1ns and precision of 1ps
`include "5_processor_design.v"
//processor testbench
module tb_processor;
	//inputs are reg datatype
	reg clock;
	reg reset;
	//outputs are wire datatype
	wire zero_flag;
	wire error_flag;
	//instantiate the processor RTL design
	processor GYMS_16 (.clock(clock),.reset(reset),.zero_flag(zero_flag),.error_flag(error_flag));
	//clock generation
	initial clock = 1'b1;
	always #5 clock = ~clock;//10ns clock time period
	//reset generation
	task reset_perform();
		begin
			@(negedge clock)
				reset = 1'b0;
			@(negedge clock)
				reset = 1'b1;
		end
	endtask//task-based reset used
	//testbench logic
	initial
		begin
			//reset, then load instructions from the binary file and finish after a while
			reset_perform();
			$readmemb("3_test_output.bin",GYMS_16.DATA.IM.instruction_memory);
			#1000 $finish;
		end
	initial
		begin
			//dump into the vcd file and display it on the terminal
			$dumpfile("7_processor_waveform.vcd");
			$dumpvars;
		end
endmodule

7_processor_waveform.vcd
$date
	Sat Aug 16 15:01:41 2025
$end
$version
	Icarus Verilog
$end
$timescale
	1ps
$end
$scope module tb_processor $end
$var wire 1 ! zero_flag $end
$var wire 1 " error_flag $end
$var reg 1 # clock $end
$var reg 1 $ reset $end
$scope module GYMS_16 $end
$var wire 1 # clock $end
$var wire 1 $ reset $end
$var wire 1 ! zero_flag $end
$var wire 1 % reg_signal_write $end
$var wire 4 & opcode [3:0] $end
$var wire 1 ' mem_signal_write $end
$var wire 1 " error_flag $end
$scope module CONTROL $end
$var wire 4 ( opcode [3:0] $end
$var parameter 3 ) addsub_inst $end
$var parameter 3 * andor_inst $end
$var parameter 3 + div_inst $end
$var parameter 3 , mem_data_inst $end
$var parameter 3 - notxor_inst $end
$var parameter 3 . reg_data_inst $end
$var parameter 3 / shift_inst $end
$var reg 1 ' mem_signal_write $end
$var reg 1 % reg_signal_write $end
$upscope $end
$scope module DATA $end
$var wire 1 # clock $end
$var wire 1 ' mem_signal_write $end
$var wire 4 0 opcode [3:0] $end
$var wire 1 % reg_signal_write $end
$var wire 1 $ reset $end
$var wire 1 ! zero_flag $end
$var wire 16 1 reg_data_read2 [15:0] $end
$var wire 16 2 reg_data_read1 [15:0] $end
$var wire 16 3 mem_data_read [15:0] $end
$var wire 16 4 instruction [15:0] $end
$var wire 1 " error_flag $end
$var wire 3 5 count_ID [2:0] $end
$var wire 3 6 count_EX [2:0] $end
$var wire 16 7 alu_res [15:0] $end
$var parameter 3 8 addsub_inst $end
$var parameter 3 9 andor_inst $end
$var parameter 4 : arith_add $end
$var parameter 4 ; arith_div $end
$var parameter 4 < arith_sub $end
$var parameter 4 = bit_and $end
$var parameter 4 > bit_not $end
$var parameter 4 ? bit_or $end
$var parameter 4 @ bit_xor $end
$var parameter 3 A div_inst $end
$var parameter 3 B mem_data_inst $end
$var parameter 3 C nop $end
$var parameter 32 D nop_width $end
$var parameter 3 E notxor_inst $end
$var parameter 3 F reg_data_inst $end
$var parameter 4 G shift_ari_left $end
$var parameter 4 H shift_ari_right $end
$var parameter 3 I shift_inst $end
$var parameter 4 J shift_log_left $end
$var parameter 4 K shift_log_right $end
$var reg 16 L EX_MEM_mem_data_write [15:0] $end
$var reg 1 M EX_MEM_mem_signal_write $end
$var reg 4 N EX_MEM_opcode [3:0] $end
$var reg 4 O EX_MEM_reg_addr_write [3:0] $end
$var reg 16 P EX_MEM_reg_data_write [15:0] $end
$var reg 16 Q ID_EX_instruction [15:0] $end
$var reg 16 R ID_EX_mem_data_write [15:0] $end
$var reg 4 S ID_EX_opcode [3:0] $end
$var reg 4 T ID_EX_operation [3:0] $end
$var reg 4 U ID_EX_reg_addr_write [3:0] $end
$var reg 16 V ID_EX_reg_data_read1 [15:0] $end
$var reg 16 W ID_EX_reg_data_read2 [15:0] $end
$var reg 16 X ID_EX_reg_data_write [15:0] $end
$var reg 16 Y IF_ID_instruction [15:0] $end
$var reg 4 Z IF_ID_opcode [3:0] $end
$var reg 8 [ IF_ID_program_counter [7:0] $end
$var reg 4 \ MEM_WB_reg_addr_write [3:0] $end
$var reg 16 ] MEM_WB_reg_data_write [15:0] $end
$var reg 1 ^ MEM_WB_reg_signal_write $end
$var reg 16 _ alu_op1 [15:0] $end
$var reg 16 ` alu_op2 [15:0] $end
$var reg 1 a counter_EX_en $end
$var reg 1 b counter_ID_en $end
$var reg 8 c mem_addr_rw [7:0] $end
$var reg 16 d mem_data_write [15:0] $end
$var reg 4 e operation [3:0] $end
$var reg 8 f program_counter [7:0] $end
$var reg 4 g reg_addr_read1 [3:0] $end
$var reg 4 h reg_addr_read2 [3:0] $end
$var reg 4 i reg_addr_write [3:0] $end
$var reg 16 j reg_data_write [15:0] $end
$scope module ALU $end
$var wire 16 k alu_op1 [15:0] $end
$var wire 16 l alu_op2 [15:0] $end
$var wire 4 m operation [3:0] $end
$var parameter 4 n arith_add $end
$var parameter 4 o arith_div $end
$var parameter 4 p arith_sub $end
$var parameter 4 q bit_and $end
$var parameter 4 r bit_not $end
$var parameter 4 s bit_or $end
$var parameter 4 t bit_xor $end
$var parameter 4 u shift_ari_left $end
$var parameter 4 v shift_ari_right $end
$var parameter 4 w shift_log_left $end
$var parameter 4 x shift_log_right $end
$var reg 16 y alu_res [15:0] $end
$var reg 1 " error_flag $end
$var reg 1 ! zero_flag $end
$upscope $end
$scope module COUNT_EX $end
$var wire 1 # clock $end
$var wire 1 a en $end
$var wire 1 $ reset $end
$var parameter 32 z width $end
$var reg 3 { count [2:0] $end
$upscope $end
$scope module COUNT_ID $end
$var wire 1 # clock $end
$var wire 1 b en $end
$var wire 1 $ reset $end
$var parameter 32 | width $end
$var reg 3 } count [2:0] $end
$upscope $end
$scope module DM $end
$var wire 1 # clock $end
$var wire 8 ~ mem_addr_rw [7:0] $end
$var wire 16 !" mem_data_write [15:0] $end
$var wire 1 M mem_signal_write $end
$var wire 16 "" mem_data_read [15:0] $end
$var integer 32 #" i [31:0] $end
$upscope $end
$scope module IM $end
$var wire 16 $" instruction [15:0] $end
$var wire 8 %" program_counter [7:0] $end
$upscope $end
$scope module RF $end
$var wire 1 # clock $end
$var wire 4 &" reg_addr_read1 [3:0] $end
$var wire 4 '" reg_addr_read2 [3:0] $end
$var wire 4 (" reg_addr_write [3:0] $end
$var wire 16 )" reg_data_read1 [15:0] $end
$var wire 16 *" reg_data_read2 [15:0] $end
$var wire 16 +" reg_data_write [15:0] $end
$var wire 1 ^ reg_signal_write $end
$var integer 32 ," i [31:0] $end
$upscope $end
$upscope $end
$upscope $end
$scope task reset_perform $end
$upscope $end
$upscope $end
$enddefinitions $end
$comment Show the parameter values. $end
$dumpall
b11 |
b11 z
b110 x
b100 w
b111 v
b101 u
b10 t
b1 s
b11 r
b0 q
b1001 p
b1010 o
b1000 n
b110 K
b100 J
b100 I
b111 H
b101 G
b1 F
b11 E
b11 D
b111 C
b0 B
b110 A
b10 @
b1 ?
b11 >
b0 =
b1001 <
b1010 ;
b1000 :
b10 9
b101 8
b100 /
b1 .
b11 -
b0 ,
b110 +
b10 *
b101 )
$end
#0
$dumpvars
b10000 ,"
bx +"
bx *"
bx )"
bx ("
bx '"
bx &"
bx %"
bx $"
b100000000 #"
bx ""
bx !"
bx ~
bx }
bx {
bx y
bx m
bx l
bx k
bx j
bx i
bx h
bx g
bx f
bx e
bx d
bx c
xb
xa
bx `
bx _
x^
bx ]
bx \
bx [
bx Z
bx Y
bx X
bx W
bx V
bx U
bx T
bx S
bx R
bx Q
bx P
bx O
bx N
xM
bx L
bx 7
bx 6
bx 5
bx 4
bx 3
bx 2
bx 1
bx 0
bx (
x'
bx &
x%
x$
1#
x"
x!
$end
#5000
0$
0#
#10000
1#
#15000
1$
0#
#20000
b10000000001000 4
b10000000001000 $"
b0 f
b0 %"
1#
#25000
0#
#30000
b1000 j
b0 i
b10 Z
b0 [
b10000000001000 Y
1#
#35000
0#
#40000
b1000 X
b10000000001000 Q
b10 S
b0 U
1#
#45000
0#
#50000
0'
1%
b1000 P
b0 O
b10 &
b10 (
b10 0
b10 N
1#
#55000
0#
#60000
0M
b1000 ]
b1000 +"
1^
b0 \
b0 ("
1#
